{
	"code":100,
    "data": [
        {
            "type": "QQ", 
            "content": "常口", 
            "gatherTime":"2013-12-12",
            "gatherDepart":"地址1",
            "gatherMan":"系统",
            "gatherReason":"重点人员"
        }, 
        {
            "type": "微信", 
            "content": "常口", 
            "gatherTime":"2013-12-12",
            "gatherDepart":"地址1",
            "gatherMan":"系统",
            "gatherReason":"重点人员"
        }, 
        {
           "type": "邮箱", 
            "content": "常口", 
            "gatherTime":"2013-12-12",
            "gatherDepart":"地址1",
            "gatherMan":"系统",
            "gatherReason":"重点人员"
        }, 
        {
            "type": "支付宝", 
            "content": "常口", 
            "gatherTime":"2013-12-12",
            "gatherDepart":"地址1",
            "gatherMan":"系统",
            "gatherReason":"重点人员"
        }
    ]
}